gpusm/__init__.py
gpusm/cli.py
gpusm/core.py
gpusm/gui.py
gpusm-0.1.0.dist-info/LICENSE
gpusm-0.1.0.dist-info/WHEEL
gpusm-0.1.0.dist-info/METADATA
gpusm-0.1.0.dist-info/RECORD
